django_wikipedia_connector/__init__.py
django_wikipedia_connector/apps.py
django_wikipedia_connector/management/__init__.py
django_wikipedia_connector/management/commands/__init__.py
django_wikipedia_connector/management/commands/import_dump.py
django_wikipedia_connector/migrations/0001_initial.py
django_wikipedia_connector/migrations/__init__.py
django_wikipedia_connector/models/__init__.py
django_wikipedia_connector/models/article.py
django_wikipedia_connector/models/article_category.py
django_wikipedia_connector/models/category.py
django_wikipedia_connector/models/page.py
django_wikipedia_connector/tests/settings.py
django_wikipedia_connector/tests/management/commands/test_import_dump.py
django_wikipedia_connector/tests/models/test_article.py
django_wikipedia_connector/tests/models/test_category.py
django_wikipedia_connector/tests/models/test_page.py
django_wikipedia_connector-0.0.1.dist-info/licenses/LICENSE
django_wikipedia_connector-0.0.1.dist-info/METADATA
django_wikipedia_connector-0.0.1.dist-info/WHEEL
django_wikipedia_connector-0.0.1.dist-info/top_level.txt
django_wikipedia_connector-0.0.1.dist-info/RECORD
